{"header":"PROCESSED on Sat, 12 Oct 2024 09:33:15 +0000 from https:\/\/prosperuniversal.com\/","files":{"cookie-law-info":{"url":"\/wp-content\/plugins\/cookie-law-info\/lite\/frontend\/js\/script.min.js","success":true,"uses_loading_strategy":false,"version":"3.2.6","last_modified":"1723634116"},"jquery-core":{"url":"\/wp-includes\/js\/jquery\/jquery.min.js","success":true,"uses_loading_strategy":false,"version":"3.7.1","last_modified":"1693223064"},"jquery-migrate":{"url":"\/wp-includes\/js\/jquery\/jquery-migrate.min.js","success":true,"uses_loading_strategy":false,"version":"3.4.1","last_modified":"1686269964"}}}